SecurityCenter-1.0.5.dist-info/METADATA
SecurityCenter-1.0.5.dist-info/WHEEL
SecurityCenter-1.0.5.dist-info/DESCRIPTION.rst
SecurityCenter-1.0.5.dist-info/metadata.json
SecurityCenter-1.0.5.dist-info/zip-safe
SecurityCenter-1.0.5.dist-info/top_level.txt
SecurityCenter-1.0.5.dist-info/RECORD
securitycenter/util.py
securitycenter/client.py
securitycenter/exc.py
securitycenter/__init__.py
securitycenter/api/file.py
securitycenter/api/auth.py
securitycenter/api/credential.py
securitycenter/api/vuln.py
securitycenter/api/scan.py
securitycenter/api/user.py
securitycenter/api/asset.py
securitycenter/api/__init__.py
securitycenter/api/_base.py
securitycenter/api/plugin.py
securitycenter/api/system.py
