Metadata-Version: 2.0
Name: SecurityCenter
Version: 1.0.5
Summary: Python wrapper for Tenable SecurityCenter API.
Home-page: https://bitbucket.org/davidism/securitycenter
Author: David Lord
Author-email: davidism@gmail.com
License: BSD
Platform: UNKNOWN
Classifier: Development Status :: 5 - Production/Stable
Classifier: Intended Audience :: Developers
Classifier: Intended Audience :: Information Technology
Classifier: License :: OSI Approved :: BSD License
Classifier: Operating System :: OS Independent
Classifier: Programming Language :: Python
Classifier: Programming Language :: Python :: 2
Classifier: Programming Language :: Python :: 3
Classifier: Topic :: System :: Systems Administration
Requires-Dist: requests
Requires-Dist: six
